molecule_proxmox/__init__.py
molecule_proxmox/driver.py
molecule_proxmox/cookiecutter/cookiecutter.json
molecule_proxmox/cookiecutter/{{cookiecutter.molecule_directory}}/{{cookiecutter.scenario_name}}/INSTALL.rst
molecule_proxmox/modules/__init__.py
molecule_proxmox/modules/proxmox_qemu_agent.py
molecule_proxmox/playbooks/create.yml
molecule_proxmox/playbooks/destroy.yml
molecule_proxmox/playbooks/prepare.yml
molecule_proxmox/playbooks/common/secrets.yml
molecule_proxmox-1.1.0.dist-info/licenses/LICENSE
molecule_proxmox-1.1.0.dist-info/METADATA
molecule_proxmox-1.1.0.dist-info/WHEEL
molecule_proxmox-1.1.0.dist-info/entry_points.txt
molecule_proxmox-1.1.0.dist-info/top_level.txt
molecule_proxmox-1.1.0.dist-info/RECORD
