Metadata-Version: 2.4
Name: molecule-proxmox
Version: 1.1.0
Summary: Proxmox Molecule Plugin :: run molecule tests using proxmox
Home-page: https://github.com/meffie/molecule-proxmox
Author: Michael Meffie
Author-email: mmeffie@sinenomine.net
Classifier: Programming Language :: Python :: 3
Classifier: Programming Language :: Python :: 3.10
Classifier: Programming Language :: Python :: 3.11
Classifier: Programming Language :: Python :: 3.12
Classifier: License :: OSI Approved :: MIT License
Classifier: Operating System :: OS Independent
Requires-Python: >=3.10
License-File: LICENSE
Requires-Dist: molecule<=25.4.0,>=6.0.0
Requires-Dist: PyYAML
Requires-Dist: proxmoxer>=1.3.1
Requires-Dist: requests
Dynamic: author
Dynamic: author-email
Dynamic: classifier
Dynamic: description
Dynamic: description-content-type
Dynamic: home-page
Dynamic: license-file
Dynamic: requires-dist
Dynamic: requires-python
Dynamic: summary
